{
  "id": "00000000-0000-0000-0000-000000000005",
  "workspaceId": "00000000-0000-0000-0000-000000000010",
  "name": "MIMIC-IV \u2192 OMOP CDM",
  "description": "Concept mapping from MIMIC-IV native source data to OMOP CDM standard concepts using the bundled OMOP vocabulary.",
  "sourceType": "database",
  "dataSourceId": "00000000-0000-0000-0000-000000000003",
  "vocabularyDataSourceId": "00000000-0000-0000-0000-000000000004",
  "conceptSetIds": [],
  "status": "in_progress",
  "badges": [
    { "id": "demo-badge-mimic", "label": "MIMIC-IV", "color": "blue" }
  ],
  "createdAt": "2026-02-10T00:00:00.000Z",
  "updatedAt": "2026-02-10T00:00:00.000Z"
}
